Workbook
Name Seção1: #REF!
Name Seção2: #REF!

Sheet Nextt
D2: Cadastre vários itens simultaneamente
D3: Preencha os dados do que quiser cadastrar.
B7: Categorias: | I7: Envie a planilha Excel
B9: Cadastro de Produtos
B10: Cadastro de Pedidos | J10: Ao terminar, lembre-se de salvar e importar a planilha Excel para o sistema.
B11: Cadastro de Marcas
B13: Operador: | I13: Como funciona?
B15: Cadastro de Segmento | I15: Este tipo de cadastro funciona de maneira similar à Matriz: você pode selecionar as informações diretamente de nossos bancos de dados e cadastrar seus produtos, pedidos, marcas e muito mais de forma automática. O melhor de tudo é que esse processo pode ser realizado em lotes, tornando tudo mais ágil e eficiente. Comece cadastrando a partir da linha 7 de cada pasta.
B16: Cadastro de Seção
B17: Cadastro de Espécie
B21: Como funciona? | I21: Precisa de ajuda?
I23: O que cada cor das células significa?
B24: Endereço > da > operação
B25: Título da operação | J25: A célula contém valores válidos. Esses serão aceitos na leitura e no cadastro do banco de dados.
B26: Atributos técnicos | C26: Campo 1 | D26: Campo 2 | E26: Campo 3 | F26: ...
B27: Obrigatório
B28: Descrição | J28: Você precisa corrigir um erro. Normalmente, quando esta cor de célula aparece, existem informações relacionadas a seleção de valores desconexos na planilha.
B29: Hyperlink
B30: Cadastro 1
B31: Cadastro 2 | J31: Não é possível inserir valores nesta célula. Isso pode ocorrer devido às restrições definidas pelas regras de negócio no banco de dados.
B32: Cadastro 3
B33: ...
B36: Atributos técnicos | I36: Expandir células
B38: Campos como 'Seção', 'Fornecedor', 'Descrição', 'Preço', entre outras, são exibidas aqui. Ou seja, todos os valores padrão necessários para o cadastro de produtos, pedidos, marcas, segmentos, seções e espécies. | I38: Para garantir que as células dos menus suspensos sejam eficientemente duplicadas e evitar erros, recomendamos que caso você opte por expandir as celulas, segure 'Ctrl' antes de clicar para realizar a expansão. Isso assegura que essas células não sofram auto-incrementação e resulte em erro na planilha.
B43: Obrigatório
B45: Essas células serão exibidas dinamicamente apenas quando representarem campos obrigatórios definidos pelas regras do banco de dados. Caso não sejam preenchidas, o cadastro por meio desta planilha não será concluído com sucesso.
B50: Descrição
B52: Neste espaço, serão exibidas informações relevantes sobre cada campo, como limite de caracteres, menus suspensos, dicas de preenchimento, entre outras orientações.
B57: Hyperlink
B59: Alguns campos podem conter hyperlinks que direcionam para outras abas da planilha, como "Cadastro de Marcas", "Cadastro de Seção (Modo Operador)" e "Cadastro de Espécie (Modo Operador)".
B63: Cadastros
B65: Nesta seção da planilha, devem ser inseridas as informações conforme os atributos técnicos indicados. Lembre-se de que cada linha representa um cadastro, permitindo uma ampla variedade e quantidade de registros que podem ser realizados diretamente no banco de dados por meio desta planilha.

Sheet Cadastro de Produtos
A1: Cadastros Básicos > Produto | R1: Atributos
A2: Cadastro de Produtos | BC2: Banco de Dados
A3: Seção | B3: Espécie | C3: Descrição | D3: Descrição Reduzida | E3: Marca | F3: Referência do Fornecedor | G3: Código Original | H3: Comprador | I3: Produto Ativo? | J3: Unidade | K3: Classificação Fiscal | L3: Origem | M3: Valor de Venda | N3: % ICMS | O3: % IPI | P3: Etiqueta Padrão | Q3: Código de Barras | R3: Cor | V3: Tamanho | BC3: Seção | BD3: Espécie | BE3: Marca | BF3: Comprador | BG3: Unidade | BH3: Classificação Fiscal | BI3: Origem | BJ3: Etiqueta Padrão
R4: Obrigatorio | V4: Obrigatorio | BC4: Os valores abaixo servem para consolidar os dados selecionados nos menus suspensos das tabelas acima e garantir uma integração eficiente com o banco de dados. Por esse motivo, essas células estão protegidas.
A5: Aviso: Os valores disponíveis para "seção" são importados automaticamente do banco de dados. | B5: Aviso: Os valores disponíveis para "espécie" são importados automaticamente do banco de dados. | C5: Máximo 50 caracteres. Dica: Se a sua descrição incluir os mesmos valores de "seção" e/ou "espécie", remova as palavras repetidas para evitar duplicidade na impressão da etiqueta. | D5: Máximo 50 caracteres. Dica: A "descrição reduzida" é uma versão compacta da "descrição", contendo apenas as palavras-chave mais relevantes. Ela será gerada automaticamente assim que um valor for inserido na célula de descrição. | E5: Aviso: Os valores disponíveis para "marca" são importados automaticamente do banco de dados. | F5: Aviso: as referências são consideradas válidas apenas se forem diferentes das já existentes no banco de dados. | G5: Caso o produto a ser cadastrado seja proveniente de uma migração de sistema, insira o seu código original no campo abaixo. | H5: Aviso: Os valores disponíveis para "comprador" são importados automaticamente do banco de dados. | I5: Por padrão, os valores de "Produto Ativo?" são definidos como 1. | J5: Aviso: Os valores disponíveis para "unidade" são importados automaticamente do banco de dados. | K5: Aviso: Os valores disponíveis para "classificação fiscal" são importados automaticamente do banco de dados. | L5: Aviso: Os valores disponíveis para "origem" são importados automaticamente do banco de dados. | M5: São aceitos apenas valores entre R$ 1,00 e R$ 99.999.999,99. | N5: São aceitos apenas valores entre 0 e 100. | O5: São aceitos apenas valores entre 0 e 100. | P5: Aviso: Os valores disponíveis para "etiqueta padrão" são importados automaticamente do banco de dados. | Q5: Máximo 20 caracteres. Aviso: são considerados válidos somente valores numéricos neste campo. | R5: Para vincular um atributo a outro, basta relacionar as células correspondentes na grade. Por exemplo, a primeira célula de "Cor" deve estar associada à primeira célula de "Tamanho", como demonstram as cores. Atenção: é essencial que a quantidade de cores seja igual à de tamanhos para garantir a correspondência correta. Aviso: é obrigatório preencher pelo menos um atributo por item.
A6: Para cadastro de 'Seção' em lotes, clique aqui | B6: Para cadastro de 'Espécie' em lotes, clique aqui | E6: Para cadastro de 'Marca' em lotes, clique aqui
BC7: =INT(INDEX('Dados Consolidados'!$R$1:$R$1000000, MATCH(A7, 'Dados Consolidados'!$A$1:$A$1000000, 0))) -> #N/A | BD7: =INT(INDEX('Dados Consolidados'!$S$1:$S$1000000, MATCH(B7, 'Dados Consolidados'!$B$1:$B$1000000, 0))) -> #N/A | BE7: =INT(INDEX('Dados Consolidados'!$T$1:$T$1000000, MATCH(E7, 'Dados Consolidados'!$E$1:$E$1000000, 0))) -> #N/A | BF7: =INT(INDEX('Dados Consolidados'!$U$1:$U$1000000, MATCH(H7, 'Dados Consolidados'!$H$1:$H$1000000, 0))) -> #N/A | BG7: =INT(INDEX('Dados Consolidados'!$V$1:$V$1000000, MATCH(J7, 'Dados Consolidados'!$J$1:$J$1000000, 0))) -> #N/A | BH7: =INT(INDEX('Dados Consolidados'!$X$1:$X$1000000, MATCH(K7, 'Dados Consolidados'!$K$1:$K$1000000, 0))) -> #N/A | BI7: =INT(INDEX('Dados Consolidados'!$Y$1:$Y$1000000, MATCH(L7, 'Dados Consolidados'!$L$1:$L$1000000, 0))) -> #N/A | BJ7: =INT(INDEX('Dados Consolidados'!$W$1:$W$1000000, MATCH(P7, 'Dados Consolidados'!$P$1:$P$1000000, 0))) -> #N/A
BC8: =INT(INDEX('Dados Consolidados'!$R$1:$R$1000000, MATCH(A8, 'Dados Consolidados'!$A$1:$A$1000000, 0))) -> #N/A | BD8: =INT(INDEX('Dados Consolidados'!$S$1:$S$1000000, MATCH(B8, 'Dados Consolidados'!$B$1:$B$1000000, 0))) -> #N/A | BE8: =INT(INDEX('Dados Consolidados'!$T$1:$T$1000000, MATCH(E8, 'Dados Consolidados'!$E$1:$E$1000000, 0))) -> #N/A | BF8: =INT(INDEX('Dados Consolidados'!$U$1:$U$1000000, MATCH(H8, 'Dados Consolidados'!$H$1:$H$1000000, 0))) -> #N/A | BG8: =INT(INDEX('Dados Consolidados'!$V$1:$V$1000000, MATCH(J8, 'Dados Consolidados'!$J$1:$J$1000000, 0))) -> #N/A | BH8: =INT(INDEX('Dados Consolidados'!$X$1:$X$1000000, MATCH(K8, 'Dados Consolidados'!$K$1:$K$1000000, 0))) -> #N/A | BI8: =INT(INDEX('Dados Consolidados'!$Y$1:$Y$1000000, MATCH(L8, 'Dados Consolidados'!$L$1:$L$1000000, 0))) -> #N/A | BJ8: =INT(INDEX('Dados Consolidados'!$W$1:$W$1000000, MATCH(P8, 'Dados Consolidados'!$P$1:$P$1000000, 0))) -> #N/A
BC9: =INT(INDEX('Dados Consolidados'!$R$1:$R$1000000, MATCH(A9, 'Dados Consolidados'!$A$1:$A$1000000, 0))) -> #N/A | BD9: =INT(INDEX('Dados Consolidados'!$S$1:$S$1000000, MATCH(B9, 'Dados Consolidados'!$B$1:$B$1000000, 0))) -> #N/A | BE9: =INT(INDEX('Dados Consolidados'!$T$1:$T$1000000, MATCH(E9, 'Dados Consolidados'!$E$1:$E$1000000, 0))) -> #N/A | BF9: =INT(INDEX('Dados Consolidados'!$U$1:$U$1000000, MATCH(H9, 'Dados Consolidados'!$H$1:$H$1000000, 0))) -> #N/A | BG9: =INT(INDEX('Dados Consolidados'!$V$1:$V$1000000, MATCH(J9, 'Dados Consolidados'!$J$1:$J$1000000, 0))) -> #N/A | BH9: =INT(INDEX('Dados Consolidados'!$X$1:$X$1000000, MATCH(K9, 'Dados Consolidados'!$K$1:$K$1000000, 0))) -> #N/A | BI9: =INT(INDEX('Dados Consolidados'!$Y$1:$Y$1000000, MATCH(L9, 'Dados Consolidados'!$L$1:$L$1000000, 0))) -> #N/A | BJ9: =INT(INDEX('Dados Consolidados'!$W$1:$W$1000000, MATCH(P9, 'Dados Consolidados'!$P$1:$P$1000000, 0))) -> #N/A
BC10: =INT(INDEX('Dados Consolidados'!$R$1:$R$1000000, MATCH(A10, 'Dados Consolidados'!$A$1:$A$1000000, 0))) -> #N/A | BD10: =INT(INDEX('Dados Consolidados'!$S$1:$S$1000000, MATCH(B10, 'Dados Consolidados'!$B$1:$B$1000000, 0))) -> #N/A | BE10: =INT(INDEX('Dados Consolidados'!$T$1:$T$1000000, MATCH(E10, 'Dados Consolidados'!$E$1:$E$1000000, 0))) -> #N/A | BF10: =INT(INDEX('Dados Consolidados'!$U$1:$U$1000000, MATCH(H10, 'Dados Consolidados'!$H$1:$H$1000000, 0))) -> #N/A | BG10: =INT(INDEX('Dados Consolidados'!$V$1:$V$1000000, MATCH(J10, 'Dados Consolidados'!$J$1:$J$1000000, 0))) -> #N/A | BH10: =INT(INDEX('Dados Consolidados'!$X$1:$X$1000000, MATCH(K10, 'Dados Consolidados'!$K$1:$K$1000000, 0))) -> #N/A | BI10: =INT(INDEX('Dados Consolidados'!$Y$1:$Y$1000000, MATCH(L10, 'Dados Consolidados'!$L$1:$L$1000000, 0))) -> #N/A | BJ10: =INT(INDEX('Dados Consolidados'!$W$1:$W$1000000, MATCH(P10, 'Dados Consolidados'!$P$1:$P$1000000, 0))) -> #N/A
BC11: =INT(INDEX('Dados Consolidados'!$R$1:$R$1000000, MATCH(A11, 'Dados Consolidados'!$A$1:$A$1000000, 0))) -> #N/A | BD11: =INT(INDEX('Dados Consolidados'!$S$1:$S$1000000, MATCH(B11, 'Dados Consolidados'!$B$1:$B$1000000, 0))) -> #N/A | BE11: =INT(INDEX('Dados Consolidados'!$T$1:$T$1000000, MATCH(E11, 'Dados Consolidados'!$E$1:$E$1000000, 0))) -> #N/A | BF11: =INT(INDEX('Dados Consolidados'!$U$1:$U$1000000, MATCH(H11, 'Dados Consolidados'!$H$1:$H$1000000, 0))) -> #N/A | BG11: =INT(INDEX('Dados Consolidados'!$V$1:$V$1000000, MATCH(J11, 'Dados Consolidados'!$J$1:$J$1000000, 0))) -> #N/A | BH11: =INT(INDEX('Dados Consolidados'!$X$1:$X$1000000, MATCH(K11, 'Dados Consolidados'!$K$1:$K$1000000, 0))) -> #N/A | BI11: =INT(INDEX('Dados Consolidados'!$Y$1:$Y$1000000, MATCH(L11, 'Dados Consolidados'!$L$1:$L$1000000, 0))) -> #N/A | BJ11: =INT(INDEX('Dados Consolidados'!$W$1:$W$1000000, MATCH(P11, 'Dados Consolidados'!$P$1:$P$1000000, 0))) -> #N/A
BC12: =INT(INDEX('Dados Consolidados'!$R$1:$R$1000000, MATCH(A12, 'Dados Consolidados'!$A$1:$A$1000000, 0))) -> #N/A | BD12: =INT(INDEX('Dados Consolidados'!$S$1:$S$1000000, MATCH(B12, 'Dados Consolidados'!$B$1:$B$1000000, 0))) -> #N/A | BE12: =INT(INDEX('Dados Consolidados'!$T$1:$T$1000000, MATCH(E12, 'Dados Consolidados'!$E$1:$E$1000000, 0))) -> #N/A | BF12: =INT(INDEX('Dados Consolidados'!$U$1:$U$1000000, MATCH(H12, 'Dados Consolidados'!$H$1:$H$1000000, 0))) -> #N/A | BG12: =INT(INDEX('Dados Consolidados'!$V$1:$V$1000000, MATCH(J12, 'Dados Consolidados'!$J$1:$J$1000000, 0))) -> #N/A | BH12: =INT(INDEX('Dados Consolidados'!$X$1:$X$1000000, MATCH(K12, 'Dados Consolidados'!$K$1:$K$1000000, 0))) -> #N/A | BI12: =INT(INDEX('Dados Consolidados'!$Y$1:$Y$1000000, MATCH(L12, 'Dados Consolidados'!$L$1:$L$1000000, 0))) -> #N/A | BJ12: =INT(INDEX('Dados Consolidados'!$W$1:$W$1000000, MATCH(P12, 'Dados Consolidados'!$P$1:$P$1000000, 0))) -> #N/A
BC13: =INT(INDEX('Dados Consolidados'!$R$1:$R$1000000, MATCH(A13, 'Dados Consolidados'!$A$1:$A$1000000, 0))) -> #N/A | BD13: =INT(INDEX('Dados Consolidados'!$S$1:$S$1000000, MATCH(B13, 'Dados Consolidados'!$B$1:$B$1000000, 0))) -> #N/A | BE13: =INT(INDEX('Dados Consolidados'!$T$1:$T$1000000, MATCH(E13, 'Dados Consolidados'!$E$1:$E$1000000, 0))) -> #N/A | BF13: =INT(INDEX('Dados Consolidados'!$U$1:$U$1000000, MATCH(H13, 'Dados Consolidados'!$H$1:$H$1000000, 0))) -> #N/A | BG13: =INT(INDEX('Dados Consolidados'!$V$1:$V$1000000, MATCH(J13, 'Dados Consolidados'!$J$1:$J$1000000, 0))) -> #N/A | BH13: =INT(INDEX('Dados Consolidados'!$X$1:$X$1000000, MATCH(K13, 'Dados Consolidados'!$K$1:$K$1000000, 0))) -> #N/A | BI13: =INT(INDEX('Dados Consolidados'!$Y$1:$Y$1000000, MATCH(L13, 'Dados Consolidados'!$L$1:$L$1000000, 0))) -> #N/A | BJ13: =INT(INDEX('Dados Consolidados'!$W$1:$W$1000000, MATCH(P13, 'Dados Consolidados'!$P$1:$P$1000000, 0))) -> #N/A
BC14: =INT(INDEX('Dados Consolidados'!$R$1:$R$1000000, MATCH(A14, 'Dados Consolidados'!$A$1:$A$1000000, 0))) -> #N/A | BD14: =INT(INDEX('Dados Consolidados'!$S$1:$S$1000000, MATCH(B14, 'Dados Consolidados'!$B$1:$B$1000000, 0))) -> #N/A | BE14: =INT(INDEX('Dados Consolidados'!$T$1:$T$1000000, MATCH(E14, 'Dados Consolidados'!$E$1:$E$1000000, 0))) -> #N/A | BF14: =INT(INDEX('Dados Consolidados'!$U$1:$U$1000000, MATCH(H14, 'Dados Consolidados'!$H$1:$H$1000000, 0))) -> #N/A | BG14: =INT(INDEX('Dados Consolidados'!$V$1:$V$1000000, MATCH(J14, 'Dados Consolidados'!$J$1:$J$1000000, 0))) -> #N/A | BH14: =INT(INDEX('Dados Consolidados'!$X$1:$X$1000000, MATCH(K14, 'Dados Consolidados'!$K$1:$K$1000000, 0))) -> #N/A | BI14: =INT(INDEX('Dados Consolidados'!$Y$1:$Y$1000000, MATCH(L14, 'Dados Consolidados'!$L$1:$L$1000000, 0))) -> #N/A | BJ14: =INT(INDEX('Dados Consolidados'!$W$1:$W$1000000, MATCH(P14, 'Dados Consolidados'!$P$1:$P$1000000, 0))) -> #N/A
BC15: =INT(INDEX('Dados Consolidados'!$R$1:$R$1000000, MATCH(A15, 'Dados Consolidados'!$A$1:$A$1000000, 0))) -> #N/A | BD15: =INT(INDEX('Dados Consolidados'!$S$1:$S$1000000, MATCH(B15, 'Dados Consolidados'!$B$1:$B$1000000, 0))) -> #N/A | BE15: =INT(INDEX('Dados Consolidados'!$T$1:$T$1000000, MATCH(E15, 'Dados Consolidados'!$E$1:$E$1000000, 0))) -> #N/A | BF15: =INT(INDEX('Dados Consolidados'!$U$1:$U$1000000, MATCH(H15, 'Dados Consolidados'!$H$1:$H$1000000, 0))) -> #N/A | BG15: =INT(INDEX('Dados Consolidados'!$V$1:$V$1000000, MATCH(J15, 'Dados Consolidados'!$J$1:$J$1000000, 0))) -> #N/A | BH15: =INT(INDEX('Dados Consolidados'!$X$1:$X$1000000, MATCH(K15, 'Dados Consolidados'!$K$1:$K$1000000, 0))) -> #N/A | BI15: =INT(INDEX('Dados Consolidados'!$Y$1:$Y$1000000, MATCH(L15, 'Dados Consolidados'!$L$1:$L$1000000, 0))) -> #N/A | BJ15: =INT(INDEX('Dados Consolidados'!$W$1:$W$1000000, MATCH(P15, 'Dados Consolidados'!$P$1:$P$1000000, 0))) -> #N/A
BC16: =INT(INDEX('Dados Consolidados'!$R$1:$R$1000000, MATCH(A16, 'Dados Consolidados'!$A$1:$A$1000000, 0))) -> #N/A | BD16: =INT(INDEX('Dados Consolidados'!$S$1:$S$1000000, MATCH(B16, 'Dados Consolidados'!$B$1:$B$1000000, 0))) -> #N/A | BE16: =INT(INDEX('Dados Consolidados'!$T$1:$T$1000000, MATCH(E16, 'Dados Consolidados'!$E$1:$E$1000000, 0))) -> #N/A | BF16: =INT(INDEX('Dados Consolidados'!$U$1:$U$1000000, MATCH(H16, 'Dados Consolidados'!$H$1:$H$1000000, 0))) -> #N/A | BG16: =INT(INDEX('Dados Consolidados'!$V$1:$V$1000000, MATCH(J16, 'Dados Consolidados'!$J$1:$J$1000000, 0))) -> #N/A | BH16: =INT(INDEX('Dados Consolidados'!$X$1:$X$1000000, MATCH(K16, 'Dados Consolidados'!$K$1:$K$1000000, 0))) -> #N/A | BI16: =INT(INDEX('Dados Consolidados'!$Y$1:$Y$1000000, MATCH(L16, 'Dados Consolidados'!$L$1:$L$1000000, 0))) -> #N/A | BJ16: =INT(INDEX('Dados Consolidados'!$W$1:$W$1000000, MATCH(P16, 'Dados Consolidados'!$P$1:$P$1000000, 0))) -> #N/A
BC17: =INT(INDEX('Dados Consolidados'!$R$1:$R$1000000, MATCH(A17, 'Dados Consolidados'!$A$1:$A$1000000, 0))) -> #N/A | BD17: =INT(INDEX('Dados Consolidados'!$S$1:$S$1000000, MATCH(B17, 'Dados Consolidados'!$B$1:$B$1000000, 0))) -> #N/A | BE17: =INT(INDEX('Dados Consolidados'!$T$1:$T$1000000, MATCH(E17, 'Dados Consolidados'!$E$1:$E$1000000, 0))) -> #N/A | BF17: =INT(INDEX('Dados Consolidados'!$U$1:$U$1000000, MATCH(H17, 'Dados Consolidados'!$H$1:$H$1000000, 0))) -> #N/A | BG17: =INT(INDEX('Dados Consolidados'!$V$1:$V$1000000, MATCH(J17, 'Dados Consolidados'!$J$1:$J$1000000, 0))) -> #N/A | BH17: =INT(INDEX('Dados Consolidados'!$X$1:$X$1000000, MATCH(K17, 'Dados Consolidados'!$K$1:$K$1000000, 0))) -> #N/A | BI17: =INT(INDEX('Dados Consolidados'!$Y$1:$Y$1000000, MATCH(L17, 'Dados Consolidados'!$L$1:$L$1000000, 0))) -> #N/A | BJ17: =INT(INDEX('Dados Consolidados'!$W$1:$W$1000000, MATCH(P17, 'Dados Consolidados'!$P$1:$P$1000000, 0))) -> #N/A
BC18: =INT(INDEX('Dados Consolidados'!$R$1:$R$1000000, MATCH(A18, 'Dados Consolidados'!$A$1:$A$1000000, 0))) -> #N/A | BD18: =INT(INDEX('Dados Consolidados'!$S$1:$S$1000000, MATCH(B18, 'Dados Consolidados'!$B$1:$B$1000000, 0))) -> #N/A | BE18: =INT(INDEX('Dados Consolidados'!$T$1:$T$1000000, MATCH(E18, 'Dados Consolidados'!$E$1:$E$1000000, 0))) -> #N/A | BF18: =INT(INDEX('Dados Consolidados'!$U$1:$U$1000000, MATCH(H18, 'Dados Consolidados'!$H$1:$H$1000000, 0))) -> #N/A | BG18: =INT(INDEX('Dados Consolidados'!$V$1:$V$1000000, MATCH(J18, 'Dados Consolidados'!$J$1:$J$1000000, 0))) -> #N/A | BH18: =INT(INDEX('Dados Consolidados'!$X$1:$X$1000000, MATCH(K18, 'Dados Consolidados'!$K$1:$K$1000000, 0))) -> #N/A | BI18: =INT(INDEX('Dados Consolidados'!$Y$1:$Y$1000000, MATCH(L18, 'Dados Consolidados'!$L$1:$L$1000000, 0))) -> #N/A | BJ18: =INT(INDEX('Dados Consolidados'!$W$1:$W$1000000, MATCH(P18, 'Dados Consolidados'!$P$1:$P$1000000, 0))) -> #N/A
... BC1007: =INT(INDEX('Dados Consolidados'!$R$1:$R$1000000, MATCH(A1007, 'Dados Consolidados'!$A$1:$A$1000000, 0))) -> #N/A | BD1007: =INT(INDEX('Dados Consolidados'!$S$1:$S$1000000, MATCH(B1007, 'Dados Consolidados'!$B$1:$B$1000000, 0))) -> #N/A | BE1007: =INT(INDEX('Dados Consolidados'!$T$1:$T$1000000, MATCH(E1007, 'Dados Consolidados'!$E$1:$E$1000000, 0))) -> #N/A | BF1007: =INT(INDEX('Dados Consolidados'!$U$1:$U$1000000, MATCH(H1007, 'Dados Consolidados'!$H$1:$H$1000000, 0))) -> #N/A | BG1007: =INT(INDEX('Dados Consolidados'!$V$1:$V$1000000, MATCH(J1007, 'Dados Consolidados'!$J$1:$J$1000000, 0))) -> #N/A | BH1007: =INT(INDEX('Dados Consolidados'!$X$1:$X$1000000, MATCH(K1007, 'Dados Consolidados'!$K$1:$K$1000000, 0))) -> #N/A | BI1007: =INT(INDEX('Dados Consolidados'!$Y$1:$Y$1000000, MATCH(L1007, 'Dados Consolidados'!$L$1:$L$1000000, 0))) -> #N/A | BJ1007: =INT(INDEX('Dados Consolidados'!$W$1:$W$1000000, MATCH(P1007, 'Dados Consolidados'!$P$1:$P$1000000, 0))) -> #N/A

Sheet Cadastro de Pedidos
A1: Cadastros Básicos > Pedido | L1: Produtos | AF1: Grades
A2: Cadastro de Pedidos | AAA2: Banco de Dados
A3: Código Original | B3: Fornecedor | C3: Comprador | D3: Dt. Entrega Inicial | E3: Dt. Entrega Final | F3: Condição de Pagamento | G3: Qualidade | H3: Parcelas | I3: Observação | J3: Formas de Pagamento | K3: Atributo | L3: Cód. Produto | V3: Preço | AAA3: Fornecedor | AAB3: Comprador | AAC3: Condição de Pagamento | AAD3: Parcelas | AAE3: Atributo
B4: Obrigatório | C4: Obrigatório | D4: Obrigatório | E4: Obrigatório | H4: Obrigatório | J4: Obrigatório | L4: Obrigatorio | V4: Obrigatorio | AAA4: Os valores abaixo servem para consolidar os dados selecionados nos menus suspensos das tabelas acima e garantir uma integração eficiente com o banco de dados. Por esse motivo, essas células estão protegidas.
A5: Caso o pedido a ser cadastrado seja proveniente de uma migração de sistema, insira o seu código original no campo abaixo. | B5: Aviso: Os valores disponíveis para "fornecedor" são importados automaticamente do banco de dados. | C5: Aviso: Os valores disponíveis para "comprador" são importados automaticamente do banco de dados. | D5: Selecione a célula desejada para inserir uma data clicando sobre ela. | E5: Selecione a célula desejada para inserir uma data clicando sobre ela. Atenção: A data de entrega final deve ser posterior à data de entrega inicial. | F5: Aviso: Os valores disponíveis para "condição de pagamento" são importados automaticamente do banco de dados. | G5: LIVRE | H5: Aviso: Os valores disponíveis para "parcelas" são importados automaticamente do banco de dados. | I5: Máximo de 1000 caracteres. | J5: Aviso: Os valores disponíveis para "formas de pagamento" são importados automaticamente do banco de dados. Clique duas vezes para selecionar. Múltipla seleção permitida. | K5: Aviso: Os valores disponíveis para "atributo" são importados automaticamente do banco de dados. | L5: Para vincular um código de produto a um preço, basta relacionar as células correspondentes na grade. Por exemplo, a primeira célula de "Cód. Produto" deve estar associada à primeira célula de "Preço", como demonstram as cores. Atenção: é essencial que a quantidade de códigos seja igual à de preços para garantir a correspondência correta. Aviso: é obrigatório preencher pelo menos um código e preço por cadastro. O código de produto deve conter exatamente 9 dígitos e ser um número inteiro.
AAA7: =(INDEX('Dados Pedido'!$DY$1:$DY$1000000,MATCH(B7,'Dados Pedido'!$B$1:$B$1000000,0))) -> #N/A | AAB7: =(INDEX('Dados Pedido'!$DZ$1:$DZ$100000,MATCH(C7,'Dados Pedido'!$C$1:$C$100000,0))) -> #N/A | AAC7: =(INDEX('Dados Pedido'!$EC$1:$EC$100000,MATCH(F7,'Dados Pedido'!$F$1:$F$100000,0))) -> #N/A | AAD7: =(INDEX('Dados Pedido'!$EA$1:$EA$100000,MATCH(H7,'Dados Pedido'!$H$1:$H$100000,0))) -> #N/A | AAE7: =(INDEX('Dados Pedido'!$EB$1:$EB$100000,MATCH(K7,'Dados Pedido'!$K$1:$K$100000,0))) -> #N/A
G8: 100 | AAA8: =(INDEX('Dados Pedido'!$DY$1:$DY$1000000,MATCH(B8,'Dados Pedido'!$B$1:$B$1000000,0))) -> #N/A | AAB8: =(INDEX('Dados Pedido'!$DZ$1:$DZ$100000,MATCH(C8,'Dados Pedido'!$C$1:$C$100000,0))) -> #N/A | AAC8: =(INDEX('Dados Pedido'!$EC$1:$EC$100000,MATCH(F8,'Dados Pedido'!$F$1:$F$100000,0))) -> #N/A | AAD8: =(INDEX('Dados Pedido'!$EA$1:$EA$100000,MATCH(H8,'Dados Pedido'!$H$1:$H$100000,0))) -> #N/A | AAE8: =(INDEX('Dados Pedido'!$EB$1:$EB$100000,MATCH(K8,'Dados Pedido'!$K$1:$K$100000,0))) -> #N/A
G9: 100 | AAA9: =(INDEX('Dados Pedido'!$DY$1:$DY$1000000,MATCH(B9,'Dados Pedido'!$B$1:$B$1000000,0))) -> #N/A | AAB9: =(INDEX('Dados Pedido'!$DZ$1:$DZ$100000,MATCH(C9,'Dados Pedido'!$C$1:$C$100000,0))) -> #N/A | AAC9: =(INDEX('Dados Pedido'!$EC$1:$EC$100000,MATCH(F9,'Dados Pedido'!$F$1:$F$100000,0))) -> #N/A | AAD9: =(INDEX('Dados Pedido'!$EA$1:$EA$100000,MATCH(H9,'Dados Pedido'!$H$1:$H$100000,0))) -> #N/A | AAE9: =(INDEX('Dados Pedido'!$EB$1:$EB$100000,MATCH(K9,'Dados Pedido'!$K$1:$K$100000,0))) -> #N/A
G10: 100 | AAA10: =(INDEX('Dados Pedido'!$DY$1:$DY$1000000,MATCH(B10,'Dados Pedido'!$B$1:$B$1000000,0))) -> #N/A | AAB10: =(INDEX('Dados Pedido'!$DZ$1:$DZ$100000,MATCH(C10,'Dados Pedido'!$C$1:$C$100000,0))) -> #N/A | AAC10: =(INDEX('Dados Pedido'!$EC$1:$EC$100000,MATCH(F10,'Dados Pedido'!$F$1:$F$100000,0))) -> #N/A | AAD10: =(INDEX('Dados Pedido'!$EA$1:$EA$100000,MATCH(H10,'Dados Pedido'!$H$1:$H$100000,0))) -> #N/A | AAE10: =(INDEX('Dados Pedido'!$EB$1:$EB$100000,MATCH(K10,'Dados Pedido'!$K$1:$K$100000,0))) -> #N/A
G11: 100 | AAA11: =(INDEX('Dados Pedido'!$DY$1:$DY$1000000,MATCH(B11,'Dados Pedido'!$B$1:$B$1000000,0))) -> #N/A | AAB11: =(INDEX('Dados Pedido'!$DZ$1:$DZ$100000,MATCH(C11,'Dados Pedido'!$C$1:$C$100000,0))) -> #N/A | AAC11: =(INDEX('Dados Pedido'!$EC$1:$EC$100000,MATCH(F11,'Dados Pedido'!$F$1:$F$100000,0))) -> #N/A | AAD11: =(INDEX('Dados Pedido'!$EA$1:$EA$100000,MATCH(H11,'Dados Pedido'!$H$1:$H$100000,0))) -> #N/A | AAE11: =(INDEX('Dados Pedido'!$EB$1:$EB$100000,MATCH(K11,'Dados Pedido'!$K$1:$K$100000,0))) -> #N/A
G12: 100 | AAA12: =(INDEX('Dados Pedido'!$DY$1:$DY$1000000,MATCH(B12,'Dados Pedido'!$B$1:$B$1000000,0))) -> #N/A | AAB12: =(INDEX('Dados Pedido'!$DZ$1:$DZ$100000,MATCH(C12,'Dados Pedido'!$C$1:$C$100000,0))) -> #N/A | AAC12: =(INDEX('Dados Pedido'!$EC$1:$EC$100000,MATCH(F12,'Dados Pedido'!$F$1:$F$100000,0))) -> #N/A | AAD12: =(INDEX('Dados Pedido'!$EA$1:$EA$100000,MATCH(H12,'Dados Pedido'!$H$1:$H$100000,0))) -> #N/A | AAE12: =(INDEX('Dados Pedido'!$EB$1:$EB$100000,MATCH(K12,'Dados Pedido'!$K$1:$K$100000,0))) -> #N/A
G13: 100 | AAA13: =(INDEX('Dados Pedido'!$DY$1:$DY$1000000,MATCH(B13,'Dados Pedido'!$B$1:$B$1000000,0))) -> #N/A | AAB13: =(INDEX('Dados Pedido'!$DZ$1:$DZ$100000,MATCH(C13,'Dados Pedido'!$C$1:$C$100000,0))) -> #N/A | AAC13: =(INDEX('Dados Pedido'!$EC$1:$EC$100000,MATCH(F13,'Dados Pedido'!$F$1:$F$100000,0))) -> #N/A | AAD13: =(INDEX('Dados Pedido'!$EA$1:$EA$100000,MATCH(H13,'Dados Pedido'!$H$1:$H$100000,0))) -> #N/A | AAE13: =(INDEX('Dados Pedido'!$EB$1:$EB$100000,MATCH(K13,'Dados Pedido'!$K$1:$K$100000,0))) -> #N/A
G14: 100 | AAA14: =(INDEX('Dados Pedido'!$DY$1:$DY$1000000,MATCH(B14,'Dados Pedido'!$B$1:$B$1000000,0))) -> #N/A | AAB14: =(INDEX('Dados Pedido'!$DZ$1:$DZ$100000,MATCH(C14,'Dados Pedido'!$C$1:$C$100000,0))) -> #N/A | AAC14: =(INDEX('Dados Pedido'!$EC$1:$EC$100000,MATCH(F14,'Dados Pedido'!$F$1:$F$100000,0))) -> #N/A | AAD14: =(INDEX('Dados Pedido'!$EA$1:$EA$100000,MATCH(H14,'Dados Pedido'!$H$1:$H$100000,0))) -> #N/A | AAE14: =(INDEX('Dados Pedido'!$EB$1:$EB$100000,MATCH(K14,'Dados Pedido'!$K$1:$K$100000,0))) -> #N/A
G15: 100 | AAA15: =(INDEX('Dados Pedido'!$DY$1:$DY$1000000,MATCH(B15,'Dados Pedido'!$B$1:$B$1000000,0))) -> #N/A | AAB15: =(INDEX('Dados Pedido'!$DZ$1:$DZ$100000,MATCH(C15,'Dados Pedido'!$C$1:$C$100000,0))) -> #N/A | AAC15: =(INDEX('Dados Pedido'!$EC$1:$EC$100000,MATCH(F15,'Dados Pedido'!$F$1:$F$100000,0))) -> #N/A | AAD15: =(INDEX('Dados Pedido'!$EA$1:$EA$100000,MATCH(H15,'Dados Pedido'!$H$1:$H$100000,0))) -> #N/A | AAE15: =(INDEX('Dados Pedido'!$EB$1:$EB$100000,MATCH(K15,'Dados Pedido'!$K$1:$K$100000,0))) -> #N/A
G16: 100 | AAA16: =(INDEX('Dados Pedido'!$DY$1:$DY$1000000,MATCH(B16,'Dados Pedido'!$B$1:$B$1000000,0))) -> #N/A | AAB16: =(INDEX('Dados Pedido'!$DZ$1:$DZ$100000,MATCH(C16,'Dados Pedido'!$C$1:$C$100000,0))) -> #N/A | AAC16: =(INDEX('Dados Pedido'!$EC$1:$EC$100000,MATCH(F16,'Dados Pedido'!$F$1:$F$100000,0))) -> #N/A | AAD16: =(INDEX('Dados Pedido'!$EA$1:$EA$100000,MATCH(H16,'Dados Pedido'!$H$1:$H$100000,0))) -> #N/A | AAE16: =(INDEX('Dados Pedido'!$EB$1:$EB$100000,MATCH(K16,'Dados Pedido'!$K$1:$K$100000,0))) -> #N/A
G17: 100 | AAA17: =(INDEX('Dados Pedido'!$DY$1:$DY$1000000,MATCH(B17,'Dados Pedido'!$B$1:$B$1000000,0))) -> #N/A | AAB17: =(INDEX('Dados Pedido'!$DZ$1:$DZ$100000,MATCH(C17,'Dados Pedido'!$C$1:$C$100000,0))) -> #N/A | AAC17: =(INDEX('Dados Pedido'!$EC$1:$EC$100000,MATCH(F17,'Dados Pedido'!$F$1:$F$100000,0))) -> #N/A | AAD17: =(INDEX('Dados Pedido'!$EA$1:$EA$100000,MATCH(H17,'Dados Pedido'!$H$1:$H$100000,0))) -> #N/A | AAE17: =(INDEX('Dados Pedido'!$EB$1:$EB$100000,MATCH(K17,'Dados Pedido'!$K$1:$K$100000,0))) -> #N/A
G18: 100 | AAA18: =(INDEX('Dados Pedido'!$DY$1:$DY$1000000,MATCH(B18,'Dados Pedido'!$B$1:$B$1000000,0))) -> #N/A | AAB18: =(INDEX('Dados Pedido'!$DZ$1:$DZ$100000,MATCH(C18,'Dados Pedido'!$C$1:$C$100000,0))) -> #N/A | AAC18: =(INDEX('Dados Pedido'!$EC$1:$EC$100000,MATCH(F18,'Dados Pedido'!$F$1:$F$100000,0))) -> #N/A | AAD18: =(INDEX('Dados Pedido'!$EA$1:$EA$100000,MATCH(H18,'Dados Pedido'!$H$1:$H$100000,0))) -> #N/A | AAE18: =(INDEX('Dados Pedido'!$EB$1:$EB$100000,MATCH(K18,'Dados Pedido'!$K$1:$K$100000,0))) -> #N/A
G19: 100 | AAA19: =(INDEX('Dados Pedido'!$DY$1:$DY$1000000,MATCH(B19,'Dados Pedido'!$B$1:$B$1000000,0))) -> #N/A | AAB19: =(INDEX('Dados Pedido'!$DZ$1:$DZ$100000,MATCH(C19,'Dados Pedido'!$C$1:$C$100000,0))) -> #N/A | AAC19: =(INDEX('Dados Pedido'!$EC$1:$EC$100000,MATCH(F19,'Dados Pedido'!$F$1:$F$100000,0))) -> #N/A | AAD19: =(INDEX('Dados Pedido'!$EA$1:$EA$100000,MATCH(H19,'Dados Pedido'!$H$1:$H$100000,0))) -> #N/A | AAE19: =(INDEX('Dados Pedido'!$EB$1:$EB$100000,MATCH(K19,'Dados Pedido'!$K$1:$K$100000,0))) -> #N/A
... G1007: 100 | AAA1007: =(INDEX('Dados Pedido'!$DY$1:$DY$1000000,MATCH(B1007,'Dados Pedido'!$B$1:$B$1000000,0))) -> #N/A | AAB1007: =(INDEX('Dados Pedido'!$DZ$1:$DZ$100000,MATCH(C1007,'Dados Pedido'!$C$1:$C$100000,0))) -> #N/A | AAC1007: =(INDEX('Dados Pedido'!$EC$1:$EC$100000,MATCH(F1007,'Dados Pedido'!$F$1:$F$100000,0))) -> #N/A | AAD1007: =(INDEX('Dados Pedido'!$EA$1:$EA$100000,MATCH(H1007,'Dados Pedido'!$H$1:$H$100000,0))) -> #N/A | AAE1007: =(INDEX('Dados Pedido'!$EB$1:$EB$100000,MATCH(K1007,'Dados Pedido'!$K$1:$K$100000,0))) -> #N/A

Sheet Cadastro de Marcas
A1: Cadastros Básicos > Marca
A2: Cadastro de Marcas
A3: Descrição
A4: Obrigatório
A5: Máximo 50 caracteres. As descrições de "marcas" serão consideradas válidas apenas se forem diferentes das já existentes no banco de dados.

Sheet Cadastro de Segmento
A1: Operador > Cadastro de Segmento
A2: Cadastro de Segmento
A3: Descrição
A4: Obrigatório
A5: Máximo 50 caracteres. As descrições de "segmento" serão consideradas válidas apenas se forem diferentes das já existentes no banco de dados.

Sheet Cadastro de Secao
A1: Operador > Cadastro de Seção | C1: Banco de Dados
A2: Cadastro de Seção
A3: Descrição | B3: Segmento | C3: Segmento
A4: Obrigatório | B4: Obrigatório | C4: Os valores abaixo servem para consolidar os dados selecionados nos menus suspensos das tabelas acima e garantir uma integração eficiente com o banco de dados. Por esse motivo, essas células estão protegidas.
A5: Máximo 50 caracteres. As descrições de "seção" serão consideradas válidas apenas se forem diferentes das já existentes no banco de dados. | B5: Aviso: Os valores disponíveis para "segmento" são importados automaticamente do banco de dados.
C7: =INT(INDEX('Dados Consolidados'!$AS$1:$AS$1000000, MATCH(B7, 'Dados Consolidados'!$AR$1:$AR$1000000, 0))) -> #N/A
C8: =INT(INDEX('Dados Consolidados'!$AS$1:$AS$1000000, MATCH(B8, 'Dados Consolidados'!$AR$1:$AR$1000000, 0))) -> #N/A
C9: =INT(INDEX('Dados Consolidados'!$AS$1:$AS$1000000, MATCH(B9, 'Dados Consolidados'!$AR$1:$AR$1000000, 0))) -> #N/A
C10: =INT(INDEX('Dados Consolidados'!$AS$1:$AS$1000000, MATCH(B10, 'Dados Consolidados'!$AR$1:$AR$1000000, 0))) -> #N/A
C11: =INT(INDEX('Dados Consolidados'!$AS$1:$AS$1000000, MATCH(B11, 'Dados Consolidados'!$AR$1:$AR$1000000, 0))) -> #N/A
C12: =INT(INDEX('Dados Consolidados'!$AS$1:$AS$1000000, MATCH(B12, 'Dados Consolidados'!$AR$1:$AR$1000000, 0))) -> #N/A
C13: =INT(INDEX('Dados Consolidados'!$AS$1:$AS$1000000, MATCH(B13, 'Dados Consolidados'!$AR$1:$AR$1000000, 0))) -> #N/A
C14: =INT(INDEX('Dados Consolidados'!$AS$1:$AS$1000000, MATCH(B14, 'Dados Consolidados'!$AR$1:$AR$1000000, 0))) -> #N/A
C15: =INT(INDEX('Dados Consolidados'!$AS$1:$AS$1000000, MATCH(B15, 'Dados Consolidados'!$AR$1:$AR$1000000, 0))) -> #N/A
C16: =INT(INDEX('Dados Consolidados'!$AS$1:$AS$1000000, MATCH(B16, 'Dados Consolidados'!$AR$1:$AR$1000000, 0))) -> #N/A
C17: =INT(INDEX('Dados Consolidados'!$AS$1:$AS$1000000, MATCH(B17, 'Dados Consolidados'!$AR$1:$AR$1000000, 0))) -> #N/A
C18: =INT(INDEX('Dados Consolidados'!$AS$1:$AS$1000000, MATCH(B18, 'Dados Consolidados'!$AR$1:$AR$1000000, 0))) -> #N/A
... C200: =INT(INDEX('Dados Consolidados'!$AS$1:$AS$1000000, MATCH(B200, 'Dados Consolidados'!$AR$1:$AR$1000000, 0))) -> #N/A

Sheet Cadastro de Especie
A1: Operador > Cadastro de Espécie | C1: Banco de Dados
A2: Cadastro de Espécie
A3: Descrição | B3: Seção | C3: Seção
A4: Obrigatório | B4: Obrigatório | C4: Os valores abaixo servem para consolidar os dados selecionados nos menus suspensos das tabelas acima e garantir uma integração eficiente com o banco de dados. Por esse motivo, essas células estão protegidas.
A5: Máximo 50 caracteres. As descrições de "espécie" serão consideradas válidas apenas se forem diferentes das já existentes no banco de dados. | B5: Aviso: Os valores disponíveis para "seção" são importados automaticamente do banco de dados.
C7: =INT(INDEX('Dados Consolidados'!$R$1:$R$1000000, MATCH(B7, 'Dados Consolidados'!$A$1:$A$1000000, 0))) -> #N/A
C8: =INT(INDEX('Dados Consolidados'!$R$1:$R$1000000, MATCH(B8, 'Dados Consolidados'!$A$1:$A$1000000, 0))) -> #N/A
C9: =INT(INDEX('Dados Consolidados'!$R$1:$R$1000000, MATCH(B9, 'Dados Consolidados'!$A$1:$A$1000000, 0))) -> #N/A
C10: =INT(INDEX('Dados Consolidados'!$R$1:$R$1000000, MATCH(B10, 'Dados Consolidados'!$A$1:$A$1000000, 0))) -> #N/A
C11: =INT(INDEX('Dados Consolidados'!$R$1:$R$1000000, MATCH(B11, 'Dados Consolidados'!$A$1:$A$1000000, 0))) -> #N/A
C12: =INT(INDEX('Dados Consolidados'!$R$1:$R$1000000, MATCH(B12, 'Dados Consolidados'!$A$1:$A$1000000, 0))) -> #N/A
C13: =INT(INDEX('Dados Consolidados'!$R$1:$R$1000000, MATCH(B13, 'Dados Consolidados'!$A$1:$A$1000000, 0))) -> #N/A
C14: =INT(INDEX('Dados Consolidados'!$R$1:$R$1000000, MATCH(B14, 'Dados Consolidados'!$A$1:$A$1000000, 0))) -> #N/A
C15: =INT(INDEX('Dados Consolidados'!$R$1:$R$1000000, MATCH(B15, 'Dados Consolidados'!$A$1:$A$1000000, 0))) -> #N/A
C16: =INT(INDEX('Dados Consolidados'!$R$1:$R$1000000, MATCH(B16, 'Dados Consolidados'!$A$1:$A$1000000, 0))) -> #N/A
C17: =INT(INDEX('Dados Consolidados'!$R$1:$R$1000000, MATCH(B17, 'Dados Consolidados'!$A$1:$A$1000000, 0))) -> #N/A
C18: =INT(INDEX('Dados Consolidados'!$R$1:$R$1000000, MATCH(B18, 'Dados Consolidados'!$A$1:$A$1000000, 0))) -> #N/A
... C200: =INT(INDEX('Dados Consolidados'!$R$1:$R$1000000, MATCH(B200, 'Dados Consolidados'!$A$1:$A$1000000, 0))) -> #N/A

Sheet Dados Consolidados
L1: Nacional, exceto as indicadas nos códigos 3, 4, 5 e 8; | Y1: 0
L2: Estrangeira, importação direta, exceto a indicada no código 6; | Y2: 1
L3: Estrangeira, adquirida no mercado interno, exceto a indicada no código 7; | Y3: 2
L4: Nacional: mercadoria ou bem com conteúdo de importação superior a 40% e inferior ou igual a 70%; | Y4: 3
L5: Nacional, cuja produção tenha sido feita em conformidade com os processos produtivos básicos de que tratam o Decreto-Lei nº 288/1967, e as Leis nº 8.248/1991, 8.387/1991, 10.176/2001 e 11.484/2007; | Y5: 4
L6: Nacional: mercadoria ou bem com Conteúdo de Importação inferior ou igual a 40%; | Y6: 5
L7: Estrangeira: importação direta, sem similar nacional, constante em lista de Resolução Camex e gás natural; | Y7: 6
L8: Estrangeira: adquirida no mercado interno, sem similar nacional, constante em lista de Resolução Camex e gás natural; | Y8: 7

Sheet Dados Pedido
